{
  "process": {
    "name": "chrome.exe",
    "pid": 23112,
    "path": "C:\\Program Files\\Google\\Chrome\\Application\\chrome.exe",
    "integrity": "low",
    "elevated": false,
    "enabled_privileges": [],
    "module_count": 19,
    "region_count": 1075
  },
  "modules": {
    "total": 19,
    "non_file_backed_count": 0,
    "non_file_backed": []
  },
  "memory_regions": {
    "exec_private_count": 4,
    "mz_header_in_private_count": 0,
    "high_entropy_exec_count": 0,
    "top_high_entropy_exec": []
  },
  "virtual_allocs": {
    "total_private_committed": 335,
    "exec_protect_count": 4,
    "mz_or_pe_count": 0,
    "suspicious_entries": [
      {
        "base": "0x18827D35000",
        "size_kb": 4,
        "protect": "RX",
        "entropy": 0.603,
        "entropy_label": "low",
        "has_mz": false,
        "has_pe": false
      },
      {
        "base": "0x7FF8E0000000",
        "size_kb": 4,
        "protect": "RX",
        "entropy": 0.09,
        "entropy_label": "low",
        "has_mz": false,
        "has_pe": false
      },
      {
        "base": "0x7FF8E0040000",
        "size_kb": 768,
        "protect": "RWX",
        "entropy": 5.641,
        "entropy_label": "medium",
        "has_mz": false,
        "has_pe": false
      },
      {
        "base": "0x7FFA18070000",
        "size_kb": 4,
        "protect": "RX",
        "entropy": 4.016,
        "entropy_label": "medium",
        "has_mz": false,
        "has_pe": false
      }
    ]
  },
  "protect_changes": {
    "total": 0,
    "gained_exec_count": 0,
    "lost_write_count": 0,
    "gained_exec_details": []
  },
  "write_events": {
    "changed_regions_count": 1,
    "with_confirmed_writer_pid": 1,
    "events": [
      {
        "base": "0x7FFE0000",
        "protect": "R",
        "writer_pids": [
          22620,
          22632
        ],
        "before_hex": "000000000000a00ff0821c1951000000",
        "after_hex": "000000000000a00f087e691951000000"
      }
    ]
  },
  "nt_syscall": {
    "direct_nt_imports_total": 130,
    "high_value_imports": [
      {
        "module": "sechost.dll",
        "function": "NtQueueApcThread"
      }
    ],
    "other_nt_imports_sample": [
      {
        "module": "chrome.exe",
        "function": "NtQueryInformationProcess"
      },
      {
        "module": "chrome_elf.dll",
        "function": "NtClose"
      },
      {
        "module": "chrome_elf.dll",
        "function": "NtCreateKey"
      },
      {
        "module": "chrome_elf.dll",
        "function": "NtDeleteKey"
      },
      {
        "module": "chrome_elf.dll",
        "function": "NtOpenKeyEx"
      }
    ],
    "syscall_stubs_in_private_exec": 25,
    "stubs": [
      {
        "address": "0x18827D35C32",
        "opcode": "SYSCALL (0F 05)",
        "protect": "RX",
        "context_bytes": "7f 01 75 03 0f 05 c3 cd 2e c3 0f 1f 84 00 00 00"
      },
      {
        "address": "0x18827D35C35",
        "opcode": "INT 2Eh (CD 2E)",
        "protect": "RX",
        "context_bytes": "03 0f 05 c3 cd 2e c3 0f 1f 84 00 00 00 00 00 00"
      },
      {
        "address": "0x18827D35C72",
        "opcode": "SYSCALL (0F 05)",
        "protect": "RX",
        "context_bytes": "7f 01 75 03 0f 05 c3 cd 2e c3 0f 1f 84 00 00 00"
      },
      {
        "address": "0x18827D35C75",
        "opcode": "INT 2Eh (CD 2E)",
        "protect": "RX",
        "context_bytes": "03 0f 05 c3 cd 2e c3 0f 1f 84 00 00 00 00 00 00"
      },
      {
        "address": "0x18827D35CB2",
        "opcode": "SYSCALL (0F 05)",
        "protect": "RX",
        "context_bytes": "7f 01 75 03 0f 05 c3 cd 2e c3 0f 1f 84 00 00 00"
      }
    ],
    "ntdll_exports_checked": 4,
    "ntdll_hooks_found": 0,
    "hooks": []
  },
  "threads": {
    "total": 18,
    "starting_in_private_exec": 0,
    "private_exec_threads": []
  },
  "remote_threads": {
    "new_threads_observed": 0,
    "from_external_process": 0,
    "details": []
  },
  "mapped_modules": {
    "anomalous_image_regions": 0,
    "entries": []
  },
  "handles": {
    "external_handles_total": 1,
    "dangerous_access_count": 0,
    "dangerous_handles": []
  },
  "api_activity": {
    "observation_window_ms": 1000,
    "inferred_calls": {
      "VirtualAllocEx": 0,
      "VirtualProtect": 0,
      "VirtualProtect_exec": 0,
      "WriteProcessMemory": 4,
      "CreateRemoteThread": 0
    },
    "total_events": 4,
    "event_sequence": [
      "write_memory"
    ],
    "note": "event_sequence shows DISTINCT event types in first-seen order. alloc->write->protect_exec->create_thread is the classic injection chain."
  },
  "performance": {
    "cpu_percent": 0.0,
    "working_set_mb": 73.2,
    "private_bytes_mb": 35.2,
    "handle_count": 273,
    "thread_count": 18,
    "io_read_mb": 0.22,
    "io_write_mb": 0.12
  },
  "memory_sample_highlights": {
    "total_samples_captured": 5,
    "interesting_count": 0,
    "interesting": []
  }
}